donnedessouscharles/__init__.py
donnedessouscharles/main.py
donnedessouscharles-0.1.0.dist-info/METADATA
donnedessouscharles-0.1.0.dist-info/WHEEL
donnedessouscharles-0.1.0.dist-info/RECORD
